{
  "tag": "reliability",
  "count": 7,
  "quotes": [
    {
      "id": "dijkstra-simplicity",
      "text": "Simplicity is prerequisite for reliability.",
      "author": "Edsger W. Dijkstra",
      "author_slug": "dijkstra",
      "source": "EWD498",
      "categories": [
        "wisdom",
        "complexity"
      ],
      "tags": [
        "simplicity",
        "reliability",
        "classic"
      ],
      "grug_level": 3,
      "spiciness": 1
    },
    {
      "text": "Simplicity is a prerequisite for reliability.",
      "author": "Edsger W. Dijkstra",
      "author_slug": "dijkstra",
      "categories": [
        "engineering",
        "wisdom"
      ],
      "tags": [
        "simplicity",
        "reliability"
      ],
      "grug_level": 3,
      "spiciness": 1,
      "id": "dijkstra-simplicity-is-a-prerequisite",
      "source": "Community sourced"
    },
    {
      "text": "The best developers aren't the ones who write the most clever code. They're the ones who write the most boring code that works.",
      "author": "based",
      "author_slug": "based",
      "categories": [
        "engineering",
        "wisdom"
      ],
      "tags": [
        "boring-code",
        "reliability"
      ],
      "grug_level": 3,
      "spiciness": 2,
      "id": "based-the-best-developers-arent",
      "source": "Community sourced"
    },
    {
      "text": "Every production database needs a backup. Every backup needs a test. Every test needs a schedule.",
      "author": "based",
      "author_slug": "based",
      "categories": [
        "engineering"
      ],
      "tags": [
        "backups",
        "reliability"
      ],
      "grug_level": 3,
      "spiciness": 1,
      "id": "based-every-production-database-needs",
      "source": "Community sourced"
    },
    {
      "text": "The best message queue is the one that never loses messages. The second best is the one that's easy to debug when it does.",
      "author": "based",
      "author_slug": "based",
      "categories": [
        "engineering"
      ],
      "tags": [
        "queues",
        "reliability"
      ],
      "grug_level": 3,
      "spiciness": 2,
      "id": "based-the-best-message-queue",
      "source": "Community sourced"
    },
    {
      "text": "Your database is your system's memory. Treat it with respect. Backup it. Index it. Never let it forget.",
      "author": "based",
      "author_slug": "based",
      "categories": [
        "engineering"
      ],
      "tags": [
        "database",
        "reliability"
      ],
      "grug_level": 3,
      "spiciness": 1,
      "id": "based-your-database-is-your",
      "source": "Community sourced"
    },
    {
      "text": "Your SaaS should be so reliable that outages are news, not routine.",
      "author": "based",
      "author_slug": "based",
      "categories": [
        "saas"
      ],
      "tags": [
        "reliability",
        "uptime"
      ],
      "grug_level": 3,
      "spiciness": 2,
      "id": "based-your-saas-should-be-650",
      "source": "Community sourced"
    }
  ]
}
