{
  "tag": "restart",
  "count": 1,
  "quotes": [
    {
      "id": "rm-rf-solution",
      "text": "Sometimes the most productive thing you can do is delete everything and start with a clear head. But maybe git stash first.",
      "author": "Unknown",
      "author_slug": "unknown",
      "source": "Programming folklore",
      "categories": [
        "funny",
        "shipping"
      ],
      "tags": [
        "deletion",
        "restart",
        "git"
      ],
      "grug_level": 5,
      "spiciness": 2
    }
  ]
}
